<?xml version="1.0" encoding="UTF-8"?>
<annotations textSource="14210884_02.txt">
    <annotation>
        <mention id="EHOST_Instance_66685" />
        <annotator id="eHOST_2010">Marjolein</annotator>
        <span start="651" end="678" />
        <spannedText>Hendrik Willem van der Kolk</spannedText>
        <creationDate>Fri May 18 13:41:45 CEST 2018</creationDate>
    </annotation>
    <classMention id="EHOST_Instance_66685">
        <mentionClass id="Person">Hendrik Willem van der Kolk</mentionClass>
    </classMention>
    <annotation>
        <mention id="EHOST_Instance_66686" />
        <annotator id="eHOST_2010">Marjolein</annotator>
        <span start="680" end="690" />
        <spannedText>geneesheer</spannedText>
        <creationDate>Fri May 18 13:41:47 CEST 2018</creationDate>
    </annotation>
    <stringSlotMention id="EHOST_Instance_66707">
        <mentionSlot id="ProfessionOf" />
        <stringSlotMentionValue value="Father" />
    </stringSlotMention>
    <complexSlotMention id="EHOST_Instance_66708">
        <mentionSlot id="profession_holder" />
        <complexSlotMentionValue value="EHOST_Instance_66685" />
    </complexSlotMention>
    <classMention id="EHOST_Instance_66686">
        <hasSlotMention id="EHOST_Instance_66707" />
        <hasSlotMention id="EHOST_Instance_66708" />
        <mentionClass id="Profession">geneesheer</mentionClass>
    </classMention>
    <annotation>
        <mention id="EHOST_Instance_66687" />
        <annotator id="eHOST_2010">Marjolein</annotator>
        <span start="714" end="741" />
        <spannedText>secretaris bij de grietenij</spannedText>
        <creationDate>Fri May 18 13:42:05 CEST 2018</creationDate>
    </annotation>
    <stringSlotMention id="EHOST_Instance_66709">
        <mentionSlot id="ProfessionOf" />
        <stringSlotMentionValue value="Father" />
    </stringSlotMention>
    <complexSlotMention id="EHOST_Instance_66710">
        <mentionSlot id="profession_holder" />
        <complexSlotMentionValue value="EHOST_Instance_66685" />
    </complexSlotMention>
    <classMention id="EHOST_Instance_66687">
        <hasSlotMention id="EHOST_Instance_66709" />
        <hasSlotMention id="EHOST_Instance_66710" />
        <mentionClass id="Profession">secretaris bij de grietenij</mentionClass>
    </classMention>
    <annotation>
        <mention id="EHOST_Instance_66688" />
        <annotator id="eHOST_2010">Marjolein</annotator>
        <span start="802" end="828" />
        <spannedText>Jaco&amp;#173;bus van der Kolk</spannedText>
        <creationDate>Fri May 18 13:42:29 CEST 2018</creationDate>
    </annotation>
    <classMention id="EHOST_Instance_66688">
        <mentionClass id="Person">Jaco&amp;#173;bus van der Kolk</mentionClass>
    </classMention>
    <annotation>
        <mention id="EHOST_Instance_66689" />
        <annotator id="eHOST_2010">Marjolein</annotator>
        <span start="834" end="858" />
        <spannedText>meester was in de regten</spannedText>
        <creationDate>Fri May 18 13:42:35 CEST 2018</creationDate>
    </annotation>
    <stringSlotMention id="EHOST_Instance_66711">
        <mentionSlot id="ProfessionOf" />
        <stringSlotMentionValue value="OtherFamilyMember" />
    </stringSlotMention>
    <complexSlotMention id="EHOST_Instance_66712">
        <mentionSlot id="profession_holder" />
        <complexSlotMentionValue value="EHOST_Instance_66688" />
    </complexSlotMention>
    <classMention id="EHOST_Instance_66689">
        <hasSlotMention id="EHOST_Instance_66711" />
        <hasSlotMention id="EHOST_Instance_66712" />
        <mentionClass id="Profession">meester was in de regten</mentionClass>
    </classMention>
    <annotation>
        <mention id="EHOST_Instance_66690" />
        <annotator id="eHOST_2010">Marjolein</annotator>
        <span start="862" end="892" />
        <spannedText>doc&amp;#173;tor in de geneeskunde</spannedText>
        <creationDate>Fri May 18 13:42:48 CEST 2018</creationDate>
    </annotation>
    <stringSlotMention id="EHOST_Instance_66713">
        <mentionSlot id="ProfessionOf" />
        <stringSlotMentionValue value="OtherFamilyMember" />
    </stringSlotMention>
    <complexSlotMention id="EHOST_Instance_66714">
        <mentionSlot id="profession_holder" />
        <complexSlotMentionValue value="EHOST_Instance_66688" />
    </complexSlotMention>
    <classMention id="EHOST_Instance_66690">
        <hasSlotMention id="EHOST_Instance_66713" />
        <hasSlotMention id="EHOST_Instance_66714" />
        <mentionClass id="Profession">doc&amp;#173;tor in de geneeskunde</mentionClass>
    </classMention>
    <annotation>
        <mention id="EHOST_Instance_66691" />
        <annotator id="eHOST_2010">Marjolein</annotator>
        <span start="992" end="1016" />
        <spannedText>Hoogleeraar in de regten</spannedText>
        <creationDate>Fri May 18 13:43:04 CEST 2018</creationDate>
    </annotation>
    <stringSlotMention id="EHOST_Instance_66715">
        <mentionSlot id="ProfessionOf" />
        <stringSlotMentionValue value="OtherFamilyMember" />
    </stringSlotMention>
    <complexSlotMention id="EHOST_Instance_66716">
        <mentionSlot id="profession_holder" />
        <complexSlotMentionValue value="EHOST_Instance_66692" />
    </complexSlotMention>
    <classMention id="EHOST_Instance_66691">
        <hasSlotMention id="EHOST_Instance_66715" />
        <hasSlotMention id="EHOST_Instance_66716" />
        <mentionClass id="Profession">Hoogleeraar in de regten</mentionClass>
    </classMention>
    <annotation>
        <mention id="EHOST_Instance_66692" />
        <annotator id="eHOST_2010">Marjolein</annotator>
        <span start="962" end="990" />
        <spannedText>Lodewijk Conradus ScuiioEDER</spannedText>
        <creationDate>Fri May 18 13:43:15 CEST 2018</creationDate>
    </annotation>
    <classMention id="EHOST_Instance_66692">
        <mentionClass id="Person">Lodewijk Conradus ScuiioEDER</mentionClass>
    </classMention>
    <annotation>
        <mention id="EHOST_Instance_66693" />
        <annotator id="eHOST_2010">Marjolein</annotator>
        <span start="1169" end="1180" />
        <spannedText>Hoogleeraar</spannedText>
        <creationDate>Fri May 18 13:43:28 CEST 2018</creationDate>
    </annotation>
    <stringSlotMention id="EHOST_Instance_66717">
        <mentionSlot id="ProfessionOf" />
        <stringSlotMentionValue value="OtherFamilyMember" />
    </stringSlotMention>
    <complexSlotMention id="EHOST_Instance_66718">
        <mentionSlot id="profession_holder" />
        <complexSlotMentionValue value="EHOST_Instance_66706" />
    </complexSlotMention>
    <classMention id="EHOST_Instance_66693">
        <hasSlotMention id="EHOST_Instance_66717" />
        <hasSlotMention id="EHOST_Instance_66718" />
        <mentionClass id="Profession">Hoogleeraar</mentionClass>
    </classMention>
    <annotation>
        <mention id="EHOST_Instance_66694" />
        <annotator id="eHOST_2010">Marjolein</annotator>
        <span start="2023" end="2029" />
        <spannedText>Koning</spannedText>
        <creationDate>Fri May 18 13:45:57 CEST 2018</creationDate>
    </annotation>
    <classMention id="EHOST_Instance_66694">
        <mentionClass id="Person">Koning</mentionClass>
    </classMention>
    <annotation>
        <mention id="EHOST_Instance_66695" />
        <annotator id="eHOST_2010">Marjolein</annotator>
        <span start="2013" end="2022" />
        <spannedText>predikant</spannedText>
        <creationDate>Fri May 18 13:45:59 CEST 2018</creationDate>
    </annotation>
    <stringSlotMention id="EHOST_Instance_66719">
        <mentionSlot id="ProfessionOf" />
        <stringSlotMentionValue value="NotFamily" />
    </stringSlotMention>
    <complexSlotMention id="EHOST_Instance_66720">
        <mentionSlot id="profession_holder" />
        <complexSlotMentionValue value="EHOST_Instance_66694" />
    </complexSlotMention>
    <classMention id="EHOST_Instance_66695">
        <hasSlotMention id="EHOST_Instance_66719" />
        <hasSlotMention id="EHOST_Instance_66720" />
        <mentionClass id="Profession">predikant</mentionClass>
    </classMention>
    <annotation>
        <mention id="EHOST_Instance_66696" />
        <annotator id="eHOST_2010">Marjolein</annotator>
        <span start="4789" end="4798" />
        <spannedText>G. Bakkee</spannedText>
        <creationDate>Fri May 18 13:49:00 CEST 2018</creationDate>
    </annotation>
    <classMention id="EHOST_Instance_66696">
        <mentionClass id="Person">G. Bakkee</mentionClass>
    </classMention>
    <annotation>
        <mention id="EHOST_Instance_66697" />
        <annotator id="eHOST_2010">Marjolein</annotator>
        <span start="4777" end="4788" />
        <spannedText>Hoogleeraar</spannedText>
        <creationDate>Fri May 18 13:49:02 CEST 2018</creationDate>
    </annotation>
    <stringSlotMention id="EHOST_Instance_66721">
        <mentionSlot id="ProfessionOf" />
        <stringSlotMentionValue value="NotFamily" />
    </stringSlotMention>
    <complexSlotMention id="EHOST_Instance_66722">
        <mentionSlot id="profession_holder" />
        <complexSlotMentionValue value="EHOST_Instance_66696" />
    </complexSlotMention>
    <classMention id="EHOST_Instance_66697">
        <hasSlotMention id="EHOST_Instance_66721" />
        <hasSlotMention id="EHOST_Instance_66722" />
        <mentionClass id="Profession">Hoogleeraar</mentionClass>
    </classMention>
    <annotation>
        <mention id="EHOST_Instance_66698" />
        <annotator id="eHOST_2010">Marjolein</annotator>
        <span start="5227" end="5245" />
        <spannedText>natuuronderzoekers</spannedText>
        <creationDate>Fri May 18 13:49:30 CEST 2018</creationDate>
    </annotation>
    <stringSlotMention id="EHOST_Instance_66723">
        <mentionSlot id="ProfessionOf" />
        <stringSlotMentionValue value="NotFamily" />
    </stringSlotMention>
    <complexSlotMention id="EHOST_Instance_66724">
        <mentionSlot id="profession_holder" />
        <complexSlotMentionValue value="EHOST_Instance_66699" />
    </complexSlotMention>
    <complexSlotMention id="EHOST_Instance_66725">
        <mentionSlot id="profession_holder" />
        <complexSlotMentionValue value="EHOST_Instance_66700" />
    </complexSlotMention>
    <classMention id="EHOST_Instance_66698">
        <hasSlotMention id="EHOST_Instance_66723" />
        <hasSlotMention id="EHOST_Instance_66724" />
        <hasSlotMention id="EHOST_Instance_66725" />
        <mentionClass id="Profession">natuuronderzoekers</mentionClass>
    </classMention>
    <annotation>
        <mention id="EHOST_Instance_66699" />
        <annotator id="eHOST_2010">Marjolein</annotator>
        <span start="5185" end="5189" />
        <spannedText>Kuhl</spannedText>
        <creationDate>Fri May 18 13:49:42 CEST 2018</creationDate>
    </annotation>
    <classMention id="EHOST_Instance_66699">
        <mentionClass id="Person">Kuhl</mentionClass>
    </classMention>
    <annotation>
        <mention id="EHOST_Instance_66700" />
        <annotator id="eHOST_2010">Marjolein</annotator>
        <span start="5193" end="5204" />
        <spannedText>van Hasselt</spannedText>
        <creationDate>Fri May 18 13:49:44 CEST 2018</creationDate>
    </annotation>
    <classMention id="EHOST_Instance_66700">
        <mentionClass id="Person">van Hasselt</mentionClass>
    </classMention>
    <annotation>
        <mention id="EHOST_Instance_66701" />
        <annotator id="eHOST_2010">Marjolein</annotator>
        <span start="5416" end="5426" />
        <spannedText>geneesheer</spannedText>
        <creationDate>Fri May 18 13:50:00 CEST 2018</creationDate>
    </annotation>
    <stringSlotMention id="EHOST_Instance_66726">
        <mentionSlot id="ProfessionOf" />
        <stringSlotMentionValue value="BioSubject" />
    </stringSlotMention>
    <classMention id="EHOST_Instance_66701">
        <hasSlotMention id="EHOST_Instance_66726" />
        <mentionClass id="Profession">geneesheer</mentionClass>
    </classMention>
    <annotation>
        <mention id="EHOST_Instance_66702" />
        <annotator id="eHOST_2010">Marjolein</annotator>
        <span start="5523" end="5529" />
        <spannedText>Bakkee</spannedText>
        <creationDate>Fri May 18 13:50:09 CEST 2018</creationDate>
    </annotation>
    <classMention id="EHOST_Instance_66702">
        <mentionClass id="Person">Bakkee</mentionClass>
    </classMention>
    <annotation>
        <mention id="EHOST_Instance_66703" />
        <annotator id="eHOST_2010">Marjolein</annotator>
        <span start="5511" end="5522" />
        <spannedText>Hoogleeraar</spannedText>
        <creationDate>Fri May 18 13:50:11 CEST 2018</creationDate>
    </annotation>
    <stringSlotMention id="EHOST_Instance_66727">
        <mentionSlot id="ProfessionOf" />
        <stringSlotMentionValue value="NotFamily" />
    </stringSlotMention>
    <complexSlotMention id="EHOST_Instance_66728">
        <mentionSlot id="profession_holder" />
        <complexSlotMentionValue value="EHOST_Instance_66702" />
    </complexSlotMention>
    <classMention id="EHOST_Instance_66703">
        <hasSlotMention id="EHOST_Instance_66727" />
        <hasSlotMention id="EHOST_Instance_66728" />
        <mentionClass id="Profession">Hoogleeraar</mentionClass>
    </classMention>
    <annotation>
        <mention id="EHOST_Instance_66704" />
        <annotator id="eHOST_2010">Marjolein</annotator>
        <span start="5566" end="5576" />
        <spannedText>geneesheer</spannedText>
        <creationDate>Fri May 18 13:50:19 CEST 2018</creationDate>
    </annotation>
    <stringSlotMention id="EHOST_Instance_66729">
        <mentionSlot id="ProfessionOf" />
        <stringSlotMentionValue value="BioSubject" />
    </stringSlotMention>
    <classMention id="EHOST_Instance_66704">
        <hasSlotMention id="EHOST_Instance_66729" />
        <mentionClass id="Profession">geneesheer</mentionClass>
    </classMention>
    <annotation>
        <mention id="EHOST_Instance_66705" />
        <annotator id="eHOST_2010">Marjolein</annotator>
        <span start="5736" end="5750" />
        <spannedText>ontleedkundige</spannedText>
        <creationDate>Fri May 18 13:50:36 CEST 2018</creationDate>
    </annotation>
    <stringSlotMention id="EHOST_Instance_66730">
        <mentionSlot id="ProfessionOf" />
        <stringSlotMentionValue value="BioSubject" />
    </stringSlotMention>
    <classMention id="EHOST_Instance_66705">
        <hasSlotMention id="EHOST_Instance_66730" />
        <mentionClass id="Profession">ontleedkundige</mentionClass>
    </classMention>
    <annotation>
        <mention id="EHOST_Instance_66706" />
        <annotator id="eHOST_2010">Nynke</annotator>
        <span start="1159" end="1168" />
        <spannedText>hun vader</spannedText>
        <creationDate>Fri Aug 10 11:20:33 CEST 2018</creationDate>
    </annotation>
    <classMention id="EHOST_Instance_66706">
        <mentionClass id="Person">hun vader</mentionClass>
    </classMention>
    <eHOST_Adjudication_Status version="1.0">
        <Adjudication_Selected_Annotators version="1.0" />
        <Adjudication_Selected_Classes version="1.0" />
        <Adjudication_Others>
            <CHECK_OVERLAPPED_SPANS>false</CHECK_OVERLAPPED_SPANS>
            <CHECK_ATTRIBUTES>false</CHECK_ATTRIBUTES>
            <CHECK_RELATIONSHIP>false</CHECK_RELATIONSHIP>
            <CHECK_CLASS>false</CHECK_CLASS>
            <CHECK_COMMENT>false</CHECK_COMMENT>
        </Adjudication_Others>
    </eHOST_Adjudication_Status>
</annotations>

