<?xml version="1.0" encoding="UTF-8"?>
<annotations textSource="13379375_02.txt">
    <annotation>
        <mention id="EHOST_Instance_43011" />
        <annotator id="eHOST_2010">Vincent</annotator>
        <span start="26" end="35" />
        <spannedText>schrijver</spannedText>
        <creationDate>Tue May 15 20:11:44 CEST 2018</creationDate>
    </annotation>
    <stringSlotMention id="EHOST_Instance_43059">
        <mentionSlot id="ProfessionOf" />
        <stringSlotMentionValue value="BioSubject" />
    </stringSlotMention>
    <classMention id="EHOST_Instance_43011">
        <hasSlotMention id="EHOST_Instance_43059" />
        <mentionClass id="Profession">schrijver</mentionClass>
    </classMention>
    <annotation>
        <mention id="EHOST_Instance_43012" />
        <annotator id="eHOST_2010">Vincent</annotator>
        <span start="39" end="60" />
        <spannedText>voordrachtskunstenaar</spannedText>
        <creationDate>Tue May 15 20:11:46 CEST 2018</creationDate>
    </annotation>
    <stringSlotMention id="EHOST_Instance_43060">
        <mentionSlot id="ProfessionOf" />
        <stringSlotMentionValue value="BioSubject" />
    </stringSlotMention>
    <classMention id="EHOST_Instance_43012">
        <hasSlotMention id="EHOST_Instance_43060" />
        <mentionClass id="Profession">voordrachtskunstenaar</mentionClass>
    </classMention>
    <annotation>
        <mention id="EHOST_Instance_43013" />
        <annotator id="eHOST_2010">Vincent</annotator>
        <span start="129" end="136" />
        <spannedText>graveur</spannedText>
        <creationDate>Tue May 15 20:11:57 CEST 2018</creationDate>
    </annotation>
    <stringSlotMention id="EHOST_Instance_43061">
        <mentionSlot id="ProfessionOf" />
        <stringSlotMentionValue value="Father" />
    </stringSlotMention>
    <complexSlotMention id="EHOST_Instance_43062">
        <mentionSlot id="profession_holder" />
        <complexSlotMentionValue value="EHOST_Instance_43014" />
    </complexSlotMention>
    <classMention id="EHOST_Instance_43013">
        <hasSlotMention id="EHOST_Instance_43061" />
        <hasSlotMention id="EHOST_Instance_43062" />
        <mentionClass id="Profession">graveur</mentionClass>
    </classMention>
    <annotation>
        <mention id="EHOST_Instance_43014" />
        <annotator id="eHOST_2010">Vincent</annotator>
        <span start="116" end="127" />
        <spannedText>Simon Fokke</spannedText>
        <creationDate>Tue May 15 20:12:03 CEST 2018</creationDate>
    </annotation>
    <classMention id="EHOST_Instance_43014">
        <mentionClass id="Person">Simon Fokke</mentionClass>
    </classMention>
    <annotation>
        <mention id="EHOST_Instance_43015" />
        <annotator id="eHOST_2010">Vincent</annotator>
        <span start="418" end="424" />
        <spannedText>acteur</spannedText>
        <creationDate>Tue May 15 20:13:02 CEST 2018</creationDate>
    </annotation>
    <stringSlotMention id="EHOST_Instance_43063">
        <mentionSlot id="ProfessionOf" />
        <stringSlotMentionValue value="OtherFamilyMember" />
    </stringSlotMention>
    <complexSlotMention id="EHOST_Instance_43064">
        <mentionSlot id="profession_holder" />
        <complexSlotMentionValue value="EHOST_Instance_43016" />
    </complexSlotMention>
    <classMention id="EHOST_Instance_43015">
        <hasSlotMention id="EHOST_Instance_43063" />
        <hasSlotMention id="EHOST_Instance_43064" />
        <mentionClass id="Profession">acteur</mentionClass>
    </classMention>
    <annotation>
        <mention id="EHOST_Instance_43016" />
        <annotator id="eHOST_2010">Vincent</annotator>
        <span start="426" end="437" />
        <spannedText>Arend Fokke</spannedText>
        <creationDate>Tue May 15 20:13:08 CEST 2018</creationDate>
    </annotation>
    <classMention id="EHOST_Instance_43016">
        <mentionClass id="Person">Arend Fokke</mentionClass>
    </classMention>
    <annotation>
        <mention id="EHOST_Instance_43017" />
        <annotator id="eHOST_2010">Vincent</annotator>
        <span start="508" end="521" />
        <spannedText>toneelspelers</spannedText>
        <creationDate>Tue May 15 20:13:25 CEST 2018</creationDate>
    </annotation>
    <stringSlotMention id="EHOST_Instance_43065">
        <mentionSlot id="ProfessionOf" />
        <stringSlotMentionValue value="OtherFamilyMember" />
    </stringSlotMention>
    <complexSlotMention id="EHOST_Instance_43066">
        <mentionSlot id="profession_holder" />
        <complexSlotMentionValue value="EHOST_Instance_43019" />
    </complexSlotMention>
    <complexSlotMention id="EHOST_Instance_43067">
        <mentionSlot id="profession_holder" />
        <complexSlotMentionValue value="EHOST_Instance_43018" />
    </complexSlotMention>
    <classMention id="EHOST_Instance_43017">
        <hasSlotMention id="EHOST_Instance_43065" />
        <hasSlotMention id="EHOST_Instance_43066" />
        <hasSlotMention id="EHOST_Instance_43067" />
        <mentionClass id="Profession">toneelspelers</mentionClass>
    </classMention>
    <annotation>
        <mention id="EHOST_Instance_43018" />
        <annotator id="eHOST_2010">Vincent</annotator>
        <span start="462" end="487" />
        <spannedText>Catharina Elisabeth Fokke</spannedText>
        <creationDate>Tue May 15 20:13:35 CEST 2018</creationDate>
    </annotation>
    <classMention id="EHOST_Instance_43018">
        <mentionClass id="Person">Catharina Elisabeth Fokke</mentionClass>
    </classMention>
    <annotation>
        <mention id="EHOST_Instance_43019" />
        <annotator id="eHOST_2010">Vincent</annotator>
        <span start="491" end="499" />
        <spannedText>Jan Punt</spannedText>
        <creationDate>Tue May 15 20:13:35 CEST 2018</creationDate>
    </annotation>
    <classMention id="EHOST_Instance_43019">
        <mentionClass id="Person">Jan Punt</mentionClass>
    </classMention>
    <annotation>
        <mention id="EHOST_Instance_43020" />
        <annotator id="eHOST_2010">Vincent</annotator>
        <span start="581" end="588" />
        <spannedText>graveur</spannedText>
        <creationDate>Tue May 15 20:13:44 CEST 2018</creationDate>
    </annotation>
    <stringSlotMention id="EHOST_Instance_43068">
        <mentionSlot id="ProfessionOf" />
        <stringSlotMentionValue value="Father" />
    </stringSlotMention>
    <complexSlotMention id="EHOST_Instance_43069">
        <mentionSlot id="profession_holder" />
        <complexSlotMentionValue value="EHOST_Instance_43021" />
    </complexSlotMention>
    <classMention id="EHOST_Instance_43020">
        <hasSlotMention id="EHOST_Instance_43068" />
        <hasSlotMention id="EHOST_Instance_43069" />
        <mentionClass id="Profession">graveur</mentionClass>
    </classMention>
    <annotation>
        <mention id="EHOST_Instance_43021" />
        <annotator id="eHOST_2010">Vincent</annotator>
        <span start="546" end="557" />
        <spannedText>Simon Fokke</spannedText>
        <creationDate>Tue May 15 20:13:47 CEST 2018</creationDate>
    </annotation>
    <classMention id="EHOST_Instance_43021">
        <mentionClass id="Person">Simon Fokke</mentionClass>
    </classMention>
    <annotation>
        <mention id="EHOST_Instance_43022" />
        <annotator id="eHOST_2010">Vincent</annotator>
        <span start="1131" end="1138" />
        <spannedText>graveur</spannedText>
        <creationDate>Tue May 15 20:14:31 CEST 2018</creationDate>
    </annotation>
    <stringSlotMention id="EHOST_Instance_43070">
        <mentionSlot id="ProfessionOf" />
        <stringSlotMentionValue value="NotFamily" />
    </stringSlotMention>
    <classMention id="EHOST_Instance_43022">
        <hasSlotMention id="EHOST_Instance_43070" />
        <mentionClass id="Profession">graveur</mentionClass>
    </classMention>
    <annotation>
        <mention id="EHOST_Instance_43023" />
        <annotator id="eHOST_2010">Vincent</annotator>
        <span start="1193" end="1201" />
        <spannedText>geleerde</spannedText>
        <creationDate>Tue May 15 20:15:03 CEST 2018</creationDate>
    </annotation>
    <stringSlotMention id="EHOST_Instance_43071">
        <mentionSlot id="ProfessionOf" />
        <stringSlotMentionValue value="NotFamily" />
    </stringSlotMention>
    <complexSlotMention id="EHOST_Instance_43072">
        <mentionSlot id="profession_holder" />
        <complexSlotMentionValue value="EHOST_Instance_43024" />
    </complexSlotMention>
    <classMention id="EHOST_Instance_43023">
        <hasSlotMention id="EHOST_Instance_43071" />
        <hasSlotMention id="EHOST_Instance_43072" />
        <mentionClass id="Profession">geleerde</mentionClass>
    </classMention>
    <annotation>
        <mention id="EHOST_Instance_43024" />
        <annotator id="eHOST_2010">Vincent</annotator>
        <span start="1202" end="1230" />
        <spannedText>C.J. Albrecht von Pfortzheim</spannedText>
        <creationDate>Tue May 15 20:15:07 CEST 2018</creationDate>
    </annotation>
    <classMention id="EHOST_Instance_43024">
        <mentionClass id="Person">C.J. Albrecht von Pfortzheim</mentionClass>
    </classMention>
    <annotation>
        <mention id="EHOST_Instance_43025" />
        <annotator id="eHOST_2010">Vincent</annotator>
        <span start="1359" end="1367" />
        <spannedText>uitgever</spannedText>
        <creationDate>Tue May 15 20:15:52 CEST 2018</creationDate>
    </annotation>
    <stringSlotMention id="EHOST_Instance_43073">
        <mentionSlot id="ProfessionOf" />
        <stringSlotMentionValue value="NotFamily" />
    </stringSlotMention>
    <complexSlotMention id="EHOST_Instance_43074">
        <mentionSlot id="profession_holder" />
        <complexSlotMentionValue value="EHOST_Instance_43026" />
    </complexSlotMention>
    <classMention id="EHOST_Instance_43025">
        <hasSlotMention id="EHOST_Instance_43073" />
        <hasSlotMention id="EHOST_Instance_43074" />
        <mentionClass id="Profession">uitgever</mentionClass>
    </classMention>
    <annotation>
        <mention id="EHOST_Instance_43026" />
        <annotator id="eHOST_2010">Vincent</annotator>
        <span start="1368" end="1386" />
        <spannedText>Steven van Esveldt</spannedText>
        <creationDate>Tue May 15 20:15:54 CEST 2018</creationDate>
    </annotation>
    <classMention id="EHOST_Instance_43026">
        <mentionClass id="Person">Steven van Esveldt</mentionClass>
    </classMention>
    <annotation>
        <mention id="EHOST_Instance_43027" />
        <annotator id="eHOST_2010">Vincent</annotator>
        <span start="1343" end="1355" />
        <spannedText>boekverkoper</spannedText>
        <creationDate>Tue May 15 20:16:04 CEST 2018</creationDate>
    </annotation>
    <stringSlotMention id="EHOST_Instance_43075">
        <mentionSlot id="ProfessionOf" />
        <stringSlotMentionValue value="NotFamily" />
    </stringSlotMention>
    <complexSlotMention id="EHOST_Instance_43076">
        <mentionSlot id="profession_holder" />
        <complexSlotMentionValue value="EHOST_Instance_43026" />
    </complexSlotMention>
    <classMention id="EHOST_Instance_43027">
        <hasSlotMention id="EHOST_Instance_43075" />
        <hasSlotMention id="EHOST_Instance_43076" />
        <mentionClass id="Profession">boekverkoper</mentionClass>
    </classMention>
    <annotation>
        <mention id="EHOST_Instance_43028" />
        <annotator id="eHOST_2010">Vincent</annotator>
        <span start="2964" end="2971" />
        <spannedText>dichter</spannedText>
        <creationDate>Tue May 15 20:17:50 CEST 2018</creationDate>
    </annotation>
    <stringSlotMention id="EHOST_Instance_43077">
        <mentionSlot id="ProfessionOf" />
        <stringSlotMentionValue value="BioSubject" />
    </stringSlotMention>
    <classMention id="EHOST_Instance_43028">
        <hasSlotMention id="EHOST_Instance_43077" />
        <mentionClass id="Profession">dichter</mentionClass>
    </classMention>
    <annotation>
        <mention id="EHOST_Instance_43029" />
        <annotator id="eHOST_2010">Vincent</annotator>
        <span start="4404" end="4460" />
        <spannedText>lid van het schoolbestuur van de Amsterdamse Nutsschool</spannedText>
        <creationDate>Tue May 15 20:22:50 CEST 2018</creationDate>
    </annotation>
    <stringSlotMention id="EHOST_Instance_43078">
        <mentionSlot id="ProfessionOf" />
        <stringSlotMentionValue value="BioSubject" />
    </stringSlotMention>
    <classMention id="EHOST_Instance_43029">
        <hasSlotMention id="EHOST_Instance_43078" />
        <mentionClass id="Profession">lid van het schoolbestuur van de Amsterdamse Nutsschool</mentionClass>
    </classMention>
    <annotation>
        <mention id="EHOST_Instance_43030" />
        <annotator id="eHOST_2010">Vincent</annotator>
        <span start="5435" end="5442" />
        <spannedText>dichter</spannedText>
        <creationDate>Tue May 15 20:23:34 CEST 2018</creationDate>
    </annotation>
    <stringSlotMention id="EHOST_Instance_43079">
        <mentionSlot id="ProfessionOf" />
        <stringSlotMentionValue value="NotFamily" />
    </stringSlotMention>
    <complexSlotMention id="EHOST_Instance_43080">
        <mentionSlot id="profession_holder" />
        <complexSlotMentionValue value="EHOST_Instance_43031" />
    </complexSlotMention>
    <classMention id="EHOST_Instance_43030">
        <hasSlotMention id="EHOST_Instance_43079" />
        <hasSlotMention id="EHOST_Instance_43080" />
        <mentionClass id="Profession">dichter</mentionClass>
    </classMention>
    <annotation>
        <mention id="EHOST_Instance_43031" />
        <annotator id="eHOST_2010">Vincent</annotator>
        <span start="5443" end="5455" />
        <spannedText>James Beatty</spannedText>
        <creationDate>Tue May 15 20:23:39 CEST 2018</creationDate>
    </annotation>
    <classMention id="EHOST_Instance_43031">
        <mentionClass id="Person">James Beatty</mentionClass>
    </classMention>
    <annotation>
        <mention id="EHOST_Instance_43032" />
        <annotator id="eHOST_2010">Vincent</annotator>
        <span start="5470" end="5478" />
        <spannedText>geleerde</spannedText>
        <creationDate>Tue May 15 20:24:00 CEST 2018</creationDate>
    </annotation>
    <stringSlotMention id="EHOST_Instance_43081">
        <mentionSlot id="ProfessionOf" />
        <stringSlotMentionValue value="NotFamily" />
    </stringSlotMention>
    <complexSlotMention id="EHOST_Instance_43082">
        <mentionSlot id="profession_holder" />
        <complexSlotMentionValue value="EHOST_Instance_43033" />
    </complexSlotMention>
    <classMention id="EHOST_Instance_43032">
        <hasSlotMention id="EHOST_Instance_43081" />
        <hasSlotMention id="EHOST_Instance_43082" />
        <mentionClass id="Profession">geleerde</mentionClass>
    </classMention>
    <annotation>
        <mention id="EHOST_Instance_43033" />
        <annotator id="eHOST_2010">Vincent</annotator>
        <span start="5479" end="5503" />
        <spannedText>Louis Poinsinet de Sivry</spannedText>
        <creationDate>Tue May 15 20:24:03 CEST 2018</creationDate>
    </annotation>
    <classMention id="EHOST_Instance_43033">
        <mentionClass id="Person">Louis Poinsinet de Sivry</mentionClass>
    </classMention>
    <annotation>
        <mention id="EHOST_Instance_43034" />
        <annotator id="eHOST_2010">Vincent</annotator>
        <span start="6221" end="6231" />
        <spannedText>Schrijvers</spannedText>
        <creationDate>Tue May 15 20:24:48 CEST 2018</creationDate>
    </annotation>
    <stringSlotMention id="EHOST_Instance_43083">
        <mentionSlot id="ProfessionOf" />
        <stringSlotMentionValue value="NotFamily" />
    </stringSlotMention>
    <classMention id="EHOST_Instance_43034">
        <hasSlotMention id="EHOST_Instance_43083" />
        <mentionClass id="Profession">Schrijvers</mentionClass>
    </classMention>
    <annotation>
        <mention id="EHOST_Instance_43035" />
        <annotator id="eHOST_2010">Vincent</annotator>
        <span start="6602" end="6610" />
        <spannedText>sergeant</spannedText>
        <creationDate>Tue May 15 20:34:33 CEST 2018</creationDate>
    </annotation>
    <stringSlotMention id="EHOST_Instance_43084">
        <mentionSlot id="ProfessionOf" />
        <stringSlotMentionValue value="NotFamily" />
    </stringSlotMention>
    <complexSlotMention id="EHOST_Instance_43085">
        <mentionSlot id="profession_holder" />
        <complexSlotMentionValue value="EHOST_Instance_43050" />
    </complexSlotMention>
    <classMention id="EHOST_Instance_43035">
        <hasSlotMention id="EHOST_Instance_43084" />
        <hasSlotMention id="EHOST_Instance_43085" />
        <mentionClass id="Profession">sergeant</mentionClass>
    </classMention>
    <annotation>
        <mention id="EHOST_Instance_43036" />
        <annotator id="eHOST_2010">Vincent</annotator>
        <span start="7317" end="7325" />
        <spannedText>uitgever</spannedText>
        <creationDate>Tue May 15 20:35:35 CEST 2018</creationDate>
    </annotation>
    <stringSlotMention id="EHOST_Instance_43086">
        <mentionSlot id="ProfessionOf" />
        <stringSlotMentionValue value="BioSubject" />
    </stringSlotMention>
    <classMention id="EHOST_Instance_43036">
        <hasSlotMention id="EHOST_Instance_43086" />
        <mentionClass id="Profession">uitgever</mentionClass>
    </classMention>
    <annotation>
        <mention id="EHOST_Instance_43037" />
        <annotator id="eHOST_2010">Vincent</annotator>
        <span start="7330" end="7343" />
        <spannedText>boekhandelaar</spannedText>
        <creationDate>Tue May 15 20:35:37 CEST 2018</creationDate>
    </annotation>
    <stringSlotMention id="EHOST_Instance_43087">
        <mentionSlot id="ProfessionOf" />
        <stringSlotMentionValue value="BioSubject" />
    </stringSlotMention>
    <classMention id="EHOST_Instance_43037">
        <hasSlotMention id="EHOST_Instance_43087" />
        <mentionClass id="Profession">boekhandelaar</mentionClass>
    </classMention>
    <annotation>
        <mention id="EHOST_Instance_43038" />
        <annotator id="eHOST_2010">Vincent</annotator>
        <span start="7726" end="7735" />
        <spannedText>predikant</spannedText>
        <creationDate>Tue May 15 20:35:57 CEST 2018</creationDate>
    </annotation>
    <stringSlotMention id="EHOST_Instance_43088">
        <mentionSlot id="ProfessionOf" />
        <stringSlotMentionValue value="NotFamily" />
    </stringSlotMention>
    <complexSlotMention id="EHOST_Instance_43089">
        <mentionSlot id="profession_holder" />
        <complexSlotMentionValue value="EHOST_Instance_43039" />
    </complexSlotMention>
    <classMention id="EHOST_Instance_43038">
        <hasSlotMention id="EHOST_Instance_43088" />
        <hasSlotMention id="EHOST_Instance_43089" />
        <mentionClass id="Profession">predikant</mentionClass>
    </classMention>
    <annotation>
        <mention id="EHOST_Instance_43039" />
        <annotator id="eHOST_2010">Vincent</annotator>
        <span start="7736" end="7760" />
        <spannedText>Joannes Decker Zimmerman</spannedText>
        <creationDate>Tue May 15 20:35:59 CEST 2018</creationDate>
    </annotation>
    <classMention id="EHOST_Instance_43039">
        <mentionClass id="Person">Joannes Decker Zimmerman</mentionClass>
    </classMention>
    <annotation>
        <mention id="EHOST_Instance_43040" />
        <annotator id="eHOST_2010">Vincent</annotator>
        <span start="7792" end="7806" />
        <spannedText>bibliothecaris</spannedText>
        <creationDate>Tue May 15 20:36:15 CEST 2018</creationDate>
    </annotation>
    <stringSlotMention id="EHOST_Instance_43090">
        <mentionSlot id="ProfessionOf" />
        <stringSlotMentionValue value="NotFamily" />
    </stringSlotMention>
    <complexSlotMention id="EHOST_Instance_43091">
        <mentionSlot id="profession_holder" />
        <complexSlotMentionValue value="EHOST_Instance_43041" />
    </complexSlotMention>
    <classMention id="EHOST_Instance_43040">
        <hasSlotMention id="EHOST_Instance_43090" />
        <hasSlotMention id="EHOST_Instance_43091" />
        <mentionClass id="Profession">bibliothecaris</mentionClass>
    </classMention>
    <annotation>
        <mention id="EHOST_Instance_43041" />
        <annotator id="eHOST_2010">Vincent</annotator>
        <span start="7827" end="7843" />
        <spannedText>Barend Klijn Bz.</spannedText>
        <creationDate>Tue May 15 20:36:19 CEST 2018</creationDate>
    </annotation>
    <classMention id="EHOST_Instance_43041">
        <mentionClass id="Person">Barend Klijn Bz.</mentionClass>
    </classMention>
    <annotation>
        <mention id="EHOST_Instance_43042" />
        <annotator id="eHOST_2010">Vincent</annotator>
        <span start="7902" end="7911" />
        <spannedText>redacteur</spannedText>
        <creationDate>Tue May 15 20:36:28 CEST 2018</creationDate>
    </annotation>
    <stringSlotMention id="EHOST_Instance_43092">
        <mentionSlot id="ProfessionOf" />
        <stringSlotMentionValue value="BioSubject" />
    </stringSlotMention>
    <classMention id="EHOST_Instance_43042">
        <hasSlotMention id="EHOST_Instance_43092" />
        <mentionClass id="Profession">redacteur</mentionClass>
    </classMention>
    <annotation>
        <mention id="EHOST_Instance_43043" />
        <annotator id="eHOST_2010">Vincent</annotator>
        <span start="7915" end="7924" />
        <spannedText>corrector</spannedText>
        <creationDate>Tue May 15 20:36:29 CEST 2018</creationDate>
    </annotation>
    <stringSlotMention id="EHOST_Instance_43093">
        <mentionSlot id="ProfessionOf" />
        <stringSlotMentionValue value="BioSubject" />
    </stringSlotMention>
    <classMention id="EHOST_Instance_43043">
        <hasSlotMention id="EHOST_Instance_43093" />
        <mentionClass id="Profession">corrector</mentionClass>
    </classMention>
    <annotation>
        <mention id="EHOST_Instance_43044" />
        <annotator id="eHOST_2010">Vincent</annotator>
        <span start="8135" end="8177" />
        <spannedText>beambte bij het Bureau van de Stadsgriffie</spannedText>
        <creationDate>Tue May 15 20:36:48 CEST 2018</creationDate>
    </annotation>
    <stringSlotMention id="EHOST_Instance_43094">
        <mentionSlot id="ProfessionOf" />
        <stringSlotMentionValue value="BioSubject" />
    </stringSlotMention>
    <classMention id="EHOST_Instance_43044">
        <hasSlotMention id="EHOST_Instance_43094" />
        <mentionClass id="Profession">beambte bij het Bureau van de Stadsgriffie</mentionClass>
    </classMention>
    <annotation>
        <mention id="EHOST_Instance_43045" />
        <annotator id="eHOST_2010">Vincent</annotator>
        <span start="8199" end="8208" />
        <spannedText>redacteur</spannedText>
        <creationDate>Tue May 15 20:36:53 CEST 2018</creationDate>
    </annotation>
    <stringSlotMention id="EHOST_Instance_43095">
        <mentionSlot id="ProfessionOf" />
        <stringSlotMentionValue value="BioSubject" />
    </stringSlotMention>
    <classMention id="EHOST_Instance_43045">
        <hasSlotMention id="EHOST_Instance_43095" />
        <mentionClass id="Profession">redacteur</mentionClass>
    </classMention>
    <annotation>
        <mention id="EHOST_Instance_43046" />
        <annotator id="eHOST_2010">Vincent</annotator>
        <span start="8826" end="8835" />
        <spannedText>schrijver</spannedText>
        <creationDate>Tue May 15 20:37:30 CEST 2018</creationDate>
    </annotation>
    <stringSlotMention id="EHOST_Instance_43096">
        <mentionSlot id="ProfessionOf" />
        <stringSlotMentionValue value="BioSubject" />
    </stringSlotMention>
    <classMention id="EHOST_Instance_43046">
        <hasSlotMention id="EHOST_Instance_43096" />
        <mentionClass id="Profession">schrijver</mentionClass>
    </classMention>
    <annotation>
        <mention id="EHOST_Instance_43047" />
        <annotator id="eHOST_2010">Vincent</annotator>
        <span start="9486" end="9500" />
        <spannedText>redacteurswerk</spannedText>
        <creationDate>Tue May 15 20:38:54 CEST 2018</creationDate>
    </annotation>
    <stringSlotMention id="EHOST_Instance_43097">
        <mentionSlot id="ProfessionOf" />
        <stringSlotMentionValue value="BioSubject" />
    </stringSlotMention>
    <classMention id="EHOST_Instance_43047">
        <hasSlotMention id="EHOST_Instance_43097" />
        <mentionClass id="Profession">redacteurswerk</mentionClass>
    </classMention>
    <annotation>
        <mention id="EHOST_Instance_43048" />
        <annotator id="eHOST_2010">Vincent</annotator>
        <span start="9842" end="9850" />
        <spannedText>sergeant</spannedText>
        <creationDate>Tue May 15 20:39:26 CEST 2018</creationDate>
    </annotation>
    <stringSlotMention id="EHOST_Instance_43098">
        <mentionSlot id="ProfessionOf" />
        <stringSlotMentionValue value="NotFamily" />
    </stringSlotMention>
    <complexSlotMention id="EHOST_Instance_43099">
        <mentionSlot id="profession_holder" />
        <complexSlotMentionValue value="EHOST_Instance_43049" />
    </complexSlotMention>
    <classMention id="EHOST_Instance_43048">
        <hasSlotMention id="EHOST_Instance_43098" />
        <hasSlotMention id="EHOST_Instance_43099" />
        <mentionClass id="Profession">sergeant</mentionClass>
    </classMention>
    <annotation>
        <mention id="EHOST_Instance_43049" />
        <annotator id="eHOST_2010">Vincent</annotator>
        <span start="9834" end="9840" />
        <spannedText>Apollo</spannedText>
        <creationDate>Tue May 15 20:39:35 CEST 2018</creationDate>
    </annotation>
    <classMention id="EHOST_Instance_43049">
        <mentionClass id="Person">Apollo</mentionClass>
    </classMention>
    <annotation>
        <mention id="EHOST_Instance_43050" />
        <annotator id="eHOST_2010">Vincent</annotator>
        <span start="6593" end="6599" />
        <spannedText>Apollo</spannedText>
        <creationDate>Tue May 15 20:39:39 CEST 2018</creationDate>
    </annotation>
    <classMention id="EHOST_Instance_43050">
        <mentionClass id="Person">Apollo</mentionClass>
    </classMention>
    <annotation>
        <mention id="EHOST_Instance_43051" />
        <annotator id="eHOST_2010">Vincent</annotator>
        <span start="10020" end="10033" />
        <spannedText>Eerste Consul</spannedText>
        <creationDate>Tue May 15 20:39:55 CEST 2018</creationDate>
    </annotation>
    <stringSlotMention id="EHOST_Instance_43100">
        <mentionSlot id="ProfessionOf" />
        <stringSlotMentionValue value="NotFamily" />
    </stringSlotMention>
    <complexSlotMention id="EHOST_Instance_43101">
        <mentionSlot id="profession_holder" />
        <complexSlotMentionValue value="EHOST_Instance_43052" />
    </complexSlotMention>
    <classMention id="EHOST_Instance_43051">
        <hasSlotMention id="EHOST_Instance_43100" />
        <hasSlotMention id="EHOST_Instance_43101" />
        <mentionClass id="Profession">Eerste Consul</mentionClass>
    </classMention>
    <annotation>
        <mention id="EHOST_Instance_43052" />
        <annotator id="eHOST_2010">Vincent</annotator>
        <span start="10034" end="10043" />
        <spannedText>Bonaparte</spannedText>
        <creationDate>Tue May 15 20:39:57 CEST 2018</creationDate>
    </annotation>
    <classMention id="EHOST_Instance_43052">
        <mentionClass id="Person">Bonaparte</mentionClass>
    </classMention>
    <annotation>
        <mention id="EHOST_Instance_43053" />
        <annotator id="eHOST_2010">Vincent</annotator>
        <span start="11328" end="11334" />
        <spannedText>keizer</spannedText>
        <creationDate>Tue May 15 20:41:56 CEST 2018</creationDate>
    </annotation>
    <stringSlotMention id="EHOST_Instance_43102">
        <mentionSlot id="ProfessionOf" />
        <stringSlotMentionValue value="NotFamily" />
    </stringSlotMention>
    <complexSlotMention id="EHOST_Instance_43103">
        <mentionSlot id="profession_holder" />
        <complexSlotMentionValue value="EHOST_Instance_43054" />
    </complexSlotMention>
    <classMention id="EHOST_Instance_43053">
        <hasSlotMention id="EHOST_Instance_43102" />
        <hasSlotMention id="EHOST_Instance_43103" />
        <mentionClass id="Profession">keizer</mentionClass>
    </classMention>
    <annotation>
        <mention id="EHOST_Instance_43054" />
        <annotator id="eHOST_2010">Vincent</annotator>
        <span start="11335" end="11343" />
        <spannedText>Napoleon</spannedText>
        <creationDate>Tue May 15 20:41:57 CEST 2018</creationDate>
    </annotation>
    <classMention id="EHOST_Instance_43054">
        <mentionClass id="Person">Napoleon</mentionClass>
    </classMention>
    <annotation>
        <mention id="EHOST_Instance_43055" />
        <annotator id="eHOST_2010">Vincent</annotator>
        <span start="11555" end="11584" />
        <spannedText>commissarissen van de politie</spannedText>
        <creationDate>Tue May 15 20:42:10 CEST 2018</creationDate>
    </annotation>
    <stringSlotMention id="EHOST_Instance_43104">
        <mentionSlot id="ProfessionOf" />
        <stringSlotMentionValue value="NotFamily" />
    </stringSlotMention>
    <complexSlotMention id="EHOST_Instance_43105">
        <mentionSlot id="profession_holder" />
        <complexSlotMentionValue value="EHOST_Instance_43057" />
    </complexSlotMention>
    <complexSlotMention id="EHOST_Instance_43106">
        <mentionSlot id="profession_holder" />
        <complexSlotMentionValue value="EHOST_Instance_43056" />
    </complexSlotMention>
    <classMention id="EHOST_Instance_43055">
        <hasSlotMention id="EHOST_Instance_43104" />
        <hasSlotMention id="EHOST_Instance_43105" />
        <hasSlotMention id="EHOST_Instance_43106" />
        <mentionClass id="Profession">commissarissen van de politie</mentionClass>
    </classMention>
    <annotation>
        <mention id="EHOST_Instance_43056" />
        <annotator id="eHOST_2010">Vincent</annotator>
        <span start="11585" end="11599" />
        <spannedText>Willem Holtrop</spannedText>
        <creationDate>Tue May 15 20:42:12 CEST 2018</creationDate>
    </annotation>
    <classMention id="EHOST_Instance_43056">
        <mentionClass id="Person">Willem Holtrop</mentionClass>
    </classMention>
    <annotation>
        <mention id="EHOST_Instance_43057" />
        <annotator id="eHOST_2010">Vincent</annotator>
        <span start="11603" end="11629" />
        <spannedText>Bernardus Antonius Fallée</spannedText>
        <creationDate>Tue May 15 20:42:15 CEST 2018</creationDate>
    </annotation>
    <classMention id="EHOST_Instance_43057">
        <mentionClass id="Person">Bernardus Antonius Fallée</mentionClass>
    </classMention>
    <annotation>
        <mention id="EHOST_Instance_43058" />
        <annotator id="eHOST_2010">Vincent</annotator>
        <span start="14366" end="14375" />
        <spannedText>schrijver</spannedText>
        <creationDate>Tue May 15 20:47:47 CEST 2018</creationDate>
    </annotation>
    <stringSlotMention id="EHOST_Instance_43107">
        <mentionSlot id="ProfessionOf" />
        <stringSlotMentionValue value="BioSubject" />
    </stringSlotMention>
    <classMention id="EHOST_Instance_43058">
        <hasSlotMention id="EHOST_Instance_43107" />
        <mentionClass id="Profession">schrijver</mentionClass>
    </classMention>
    <eHOST_Adjudication_Status version="1.0">
        <Adjudication_Selected_Annotators version="1.0" />
        <Adjudication_Selected_Classes version="1.0" />
        <Adjudication_Others>
            <CHECK_OVERLAPPED_SPANS>false</CHECK_OVERLAPPED_SPANS>
            <CHECK_ATTRIBUTES>false</CHECK_ATTRIBUTES>
            <CHECK_RELATIONSHIP>false</CHECK_RELATIONSHIP>
            <CHECK_CLASS>false</CHECK_CLASS>
            <CHECK_COMMENT>false</CHECK_COMMENT>
        </Adjudication_Others>
    </eHOST_Adjudication_Status>
</annotations>

