<?xml version="1.0" encoding="UTF-8"?>
<annotations textSource="10020011_02.txt">
    <annotation>
        <mention id="EHOST_Instance_46749" />
        <annotator id="eHOST_2010">Kim</annotator>
        <span start="817" end="825" />
        <spannedText>chemicus</spannedText>
        <creationDate>Fri May 18 20:49:58 CEST 2018</creationDate>
    </annotation>
    <stringSlotMention id="EHOST_Instance_46762">
        <mentionSlot id="ProfessionOf" />
        <stringSlotMentionValue value="Father" />
    </stringSlotMention>
    <complexSlotMention id="EHOST_Instance_46763">
        <mentionSlot id="profession_holder" />
        <complexSlotMentionValue value="EHOST_Instance_46750" />
    </complexSlotMention>
    <classMention id="EHOST_Instance_46749">
        <hasSlotMention id="EHOST_Instance_46762" />
        <hasSlotMention id="EHOST_Instance_46763" />
        <mentionClass id="Profession">chemicus</mentionClass>
    </classMention>
    <annotation>
        <mention id="EHOST_Instance_46750" />
        <annotator id="eHOST_2010">Kim</annotator>
        <span start="788" end="798" />
        <spannedText>Zijn vader</spannedText>
        <creationDate>Fri May 18 20:50:00 CEST 2018</creationDate>
    </annotation>
    <classMention id="EHOST_Instance_46750">
        <mentionClass id="Person">Zijn vader</mentionClass>
    </classMention>
    <annotation>
        <mention id="EHOST_Instance_46751" />
        <annotator id="eHOST_2010">Kim</annotator>
        <span start="833" end="839" />
        <spannedText>leraar</spannedText>
        <creationDate>Fri May 18 20:50:04 CEST 2018</creationDate>
    </annotation>
    <stringSlotMention id="EHOST_Instance_46764">
        <mentionSlot id="ProfessionOf" />
        <stringSlotMentionValue value="Father" />
    </stringSlotMention>
    <complexSlotMention id="EHOST_Instance_46765">
        <mentionSlot id="profession_holder" />
        <complexSlotMentionValue value="EHOST_Instance_46750" />
    </complexSlotMention>
    <classMention id="EHOST_Instance_46751">
        <hasSlotMention id="EHOST_Instance_46764" />
        <hasSlotMention id="EHOST_Instance_46765" />
        <mentionClass id="Profession">leraar</mentionClass>
    </classMention>
    <annotation>
        <mention id="EHOST_Instance_46752" />
        <annotator id="eHOST_2010">Kim</annotator>
        <span start="849" end="858" />
        <spannedText>directeur</spannedText>
        <creationDate>Fri May 18 20:50:05 CEST 2018</creationDate>
    </annotation>
    <stringSlotMention id="EHOST_Instance_46766">
        <mentionSlot id="ProfessionOf" />
        <stringSlotMentionValue value="Father" />
    </stringSlotMention>
    <complexSlotMention id="EHOST_Instance_46767">
        <mentionSlot id="profession_holder" />
        <complexSlotMentionValue value="EHOST_Instance_46750" />
    </complexSlotMention>
    <classMention id="EHOST_Instance_46752">
        <hasSlotMention id="EHOST_Instance_46766" />
        <hasSlotMention id="EHOST_Instance_46767" />
        <mentionClass id="Profession">directeur</mentionClass>
    </classMention>
    <annotation>
        <mention id="EHOST_Instance_46753" />
        <annotator id="eHOST_2010">Kim</annotator>
        <span start="886" end="897" />
        <spannedText>zijn moeder</spannedText>
        <creationDate>Fri May 18 20:50:30 CEST 2018</creationDate>
    </annotation>
    <classMention id="EHOST_Instance_46753">
        <mentionClass id="Person">zijn moeder</mentionClass>
    </classMention>
    <annotation>
        <mention id="EHOST_Instance_46754" />
        <annotator id="eHOST_2010">Kim</annotator>
        <span start="921" end="931" />
        <spannedText>wiskundige</spannedText>
        <creationDate>Fri May 18 20:50:33 CEST 2018</creationDate>
    </annotation>
    <stringSlotMention id="EHOST_Instance_46768">
        <mentionSlot id="ProfessionOf" />
        <stringSlotMentionValue value="Mother" />
    </stringSlotMention>
    <complexSlotMention id="EHOST_Instance_46769">
        <mentionSlot id="profession_holder" />
        <complexSlotMentionValue value="EHOST_Instance_46753" />
    </complexSlotMention>
    <classMention id="EHOST_Instance_46754">
        <hasSlotMention id="EHOST_Instance_46768" />
        <hasSlotMention id="EHOST_Instance_46769" />
        <mentionClass id="Profession">wiskundige</mentionClass>
    </classMention>
    <annotation>
        <mention id="EHOST_Instance_46755" />
        <annotator id="eHOST_2010">Kim</annotator>
        <span start="1778" end="1789" />
        <spannedText>programmeur</spannedText>
        <creationDate>Fri May 18 20:51:02 CEST 2018</creationDate>
    </annotation>
    <stringSlotMention id="EHOST_Instance_46770">
        <mentionSlot id="ProfessionOf" />
        <stringSlotMentionValue value="BioSubject" />
    </stringSlotMention>
    <classMention id="EHOST_Instance_46755">
        <hasSlotMention id="EHOST_Instance_46770" />
        <mentionClass id="Profession">programmeur</mentionClass>
    </classMention>
    <annotation>
        <mention id="EHOST_Instance_46756" />
        <annotator id="eHOST_2010">Kim</annotator>
        <span start="2420" end="2479" />
        <spannedText>directeur van de rekenafdeling van het Mathematisch Centrum</spannedText>
        <creationDate>Fri May 18 20:51:26 CEST 2018</creationDate>
    </annotation>
    <stringSlotMention id="EHOST_Instance_46771">
        <mentionSlot id="ProfessionOf" />
        <stringSlotMentionValue value="NotFamily" />
    </stringSlotMention>
    <complexSlotMention id="EHOST_Instance_46772">
        <mentionSlot id="profession_holder" />
        <complexSlotMentionValue value="EHOST_Instance_46757" />
    </complexSlotMention>
    <classMention id="EHOST_Instance_46756">
        <hasSlotMention id="EHOST_Instance_46771" />
        <hasSlotMention id="EHOST_Instance_46772" />
        <mentionClass id="Profession">directeur van de rekenafdeling van het Mathematisch Centrum</mentionClass>
    </classMention>
    <annotation>
        <mention id="EHOST_Instance_46757" />
        <annotator id="eHOST_2010">Kim</annotator>
        <span start="2394" end="2413" />
        <spannedText>A. van Wijngaarden</spannedText>
        <creationDate>Fri May 18 20:51:28 CEST 2018</creationDate>
    </annotation>
    <classMention id="EHOST_Instance_46757">
        <mentionClass id="Person">A. van Wijngaarden</mentionClass>
    </classMention>
    <annotation>
        <mention id="EHOST_Instance_46758" />
        <annotator id="eHOST_2010">Kim</annotator>
        <span start="2632" end="2643" />
        <spannedText>programmeur</spannedText>
        <creationDate>Fri May 18 20:51:41 CEST 2018</creationDate>
    </annotation>
    <stringSlotMention id="EHOST_Instance_46773">
        <mentionSlot id="ProfessionOf" />
        <stringSlotMentionValue value="BioSubject" />
    </stringSlotMention>
    <classMention id="EHOST_Instance_46758">
        <hasSlotMention id="EHOST_Instance_46773" />
        <mentionClass id="Profession">programmeur</mentionClass>
    </classMention>
    <annotation>
        <mention id="EHOST_Instance_46759" />
        <annotator id="eHOST_2010">Kim</annotator>
        <span start="4429" end="4454" />
        <spannedText>hoogleraar in de wiskunde</spannedText>
        <creationDate>Fri May 18 20:52:51 CEST 2018</creationDate>
    </annotation>
    <stringSlotMention id="EHOST_Instance_46774">
        <mentionSlot id="ProfessionOf" />
        <stringSlotMentionValue value="BioSubject" />
    </stringSlotMention>
    <classMention id="EHOST_Instance_46759">
        <hasSlotMention id="EHOST_Instance_46774" />
        <mentionClass id="Profession">hoogleraar in de wiskunde</mentionClass>
    </classMention>
    <annotation>
        <mention id="EHOST_Instance_46760" />
        <annotator id="eHOST_2010">Marjolein</annotator>
        <span start="648" end="674" />
        <spannedText>lid van de Sectie Wiskunde</spannedText>
        <creationDate>Sun Jul 08 11:05:58 CEST 2018</creationDate>
    </annotation>
    <stringSlotMention id="EHOST_Instance_46775">
        <mentionSlot id="ProfessionOf" />
        <stringSlotMentionValue value="BioSubject" />
    </stringSlotMention>
    <classMention id="EHOST_Instance_46760">
        <hasSlotMention id="EHOST_Instance_46775" />
        <mentionClass id="Profession">lid van de Sectie Wiskunde</mentionClass>
    </classMention>
    <annotation>
        <mention id="EHOST_Instance_46761" />
        <annotator id="eHOST_2010">Marjolein</annotator>
        <span start="5075" end="5085" />
        <spannedText>mathematen</spannedText>
        <creationDate>Sun Jul 08 11:10:20 CEST 2018</creationDate>
    </annotation>
    <stringSlotMention id="EHOST_Instance_46776">
        <mentionSlot id="ProfessionOf" />
        <stringSlotMentionValue value="NotFamily" />
    </stringSlotMention>
    <classMention id="EHOST_Instance_46761">
        <hasSlotMention id="EHOST_Instance_46776" />
        <mentionClass id="Profession">mathematen</mentionClass>
    </classMention>
    <eHOST_Adjudication_Status version="1.0">
        <Adjudication_Selected_Annotators version="1.0" />
        <Adjudication_Selected_Classes version="1.0" />
        <Adjudication_Others>
            <CHECK_OVERLAPPED_SPANS>false</CHECK_OVERLAPPED_SPANS>
            <CHECK_ATTRIBUTES>false</CHECK_ATTRIBUTES>
            <CHECK_RELATIONSHIP>false</CHECK_RELATIONSHIP>
            <CHECK_CLASS>false</CHECK_CLASS>
            <CHECK_COMMENT>false</CHECK_COMMENT>
        </Adjudication_Others>
    </eHOST_Adjudication_Status>
</annotations>

